best/__init__.py
best/integration/__init__.py
best/unit/__init__.py
best/unit/conftest.py
best/unit/test_glue_session.py
best/unit/test_glue_session_demo.py
best/unit/test_session_apis.py
pulumi_onepassword-0.0.0.dist-info/LICENSE.txt
pulumi_onepassword-0.0.0.dist-info/METADATA
pulumi_onepassword-0.0.0.dist-info/WHEEL
pulumi_onepassword-0.0.0.dist-info/top_level.txt
pulumi_onepassword-0.0.0.dist-info/RECORD
