Metadata-Version: 2.1
Name: pulumi-onepassword
Version: 0.0.0
Summary: HiZXtman  sdafaf safafa sfsdf
Author: sharmajiii
Author-email: sharmaji@ict.com
Classifier: Programming Language :: Python :: 3
Classifier: License :: OSI Approved :: MIT License
Classifier: Operating System :: OS Independent
License-File: LICENSE.txt
